LICENSE
MANIFEST.in
README.md
pyproject.toml
version
loggissimo/__init__.py
loggissimo/_logger.py
loggissimo/_style.py
loggissimo/_utils.py
loggissimo/constants.py
loggissimo/exceptions.py
loggissimo/py.typed
loggissimo.egg-info/PKG-INFO
loggissimo.egg-info/SOURCES.txt
loggissimo.egg-info/dependency_links.txt
loggissimo.egg-info/requires.txt
loggissimo.egg-info/top_level.txt
tests/test_enable.py
tests/test_loglevel.py
tests/test_proc_th.py