Metadata-Version: 2.4
Name: loggissimo
Version: 1.0.7
Summary: Awesome and simple logger
Author-email: MikleSedrakyan <scriptdefender@yandex.ru>, AfanasevAndrey <scriptdefender@yandex.ru>
License: MIT License
Project-URL: Homepage, https://github.com/Sw1mmeR/loggissimo/tree/main
Requires-Python: >=3.11
License-File: LICENSE
Requires-Dist: colorcall>=0.2.1
Provides-Extra: testing
Requires-Dist: pytest==7.4.0; extra == "testing"
Dynamic: license-file
